draft_sport/__init__.py
draft_sport/ancillary/__init__.py
draft_sport/ancillary/configuration.py
draft_sport/communication/__init__.py
draft_sport/communication/challenge.py
draft_sport/communication/method.py
draft_sport/data/__init__.py
draft_sport/data/order.py
draft_sport/fantasy/__init__.py
draft_sport/fantasy/competition/__init__.py
draft_sport/fantasy/competition/competition.py
draft_sport/fantasy/competition/constants.py
draft_sport/fantasy/player/__init__.py
draft_sport/fantasy/player/profile.py
draft_sport/fantasy/position/__init__.py
draft_sport/fantasy/position/constants.py
draft_sport/fantasy/position/position.py
draft_sport/fantasy/scores/__init__.py
draft_sport/fantasy/scores/player/__init__.py
draft_sport/fantasy/scores/player/metrics.py
draft_sport/fantasy/scores/player/order_by.py
draft_sport/fantasy/scores/player/player.py
draft_sport/fantasy/scores/player/points.py
draft_sport/fantasy/scores/player/round.py
draft_sport/fantasy/scores/player/score.py
draft_sport/fantasy/scores/player/score_card.py
draft_sport/fantasy/season/__init__.py
draft_sport/fantasy/season/constants.py
draft_sport/fantasy/season/season.py
draft_sport/fantasy/team/__init__.py
draft_sport/fantasy/team/constants.py
draft_sport/fantasy/team/team.py
draft_sport/humans/__init__.py
draft_sport/humans/human.py
draft_sport/humans/name.py
draft_sport/leagues/__init__.py
draft_sport/leagues/category_requirement.py
draft_sport/leagues/composition.py
draft_sport/leagues/filled_composition.py
draft_sport/leagues/filled_requirement.py
draft_sport/leagues/invitation.py
draft_sport/leagues/league.py
draft_sport/leagues/pick.py
draft_sport/leagues/position_requirement.py
draft_sport/leagues/requirement.py
draft_sport/leagues/team.py
draft_sport/leagues/team_summary.py
draft_sport/security/__init__.py
draft_sport/security/key.py
draft_sport/security/perspective.py
draft_sport/security/secret_reset_request.py
draft_sport/security/session.py
draft_sport/store/__init__.py
draft_sport-0.0.45.dist-info/METADATA
draft_sport-0.0.45.dist-info/WHEEL
draft_sport-0.0.45.dist-info/top_level.txt
draft_sport-0.0.45.dist-info/RECORD
