Metadata-Version: 2.1
Name: draft-sport
Version: 0.0.45
Summary: Draft Sport API Library
Home-page: https://github.com/hwjeremy/draft-sport-py
Author: DraftSport
Author-email: hugh@blinkybeach.com
License: UNKNOWN
Project-URL: Github Repository, https://github.com/hwjeremy/draft-sport-py
Project-URL: About, https://github.com/hwjeremy/draft-sport-py
Keywords: library http api web application
Platform: UNKNOWN
Classifier: Development Status :: 2 - Pre-Alpha
Classifier: Intended Audience :: Developers
Classifier: License :: OSI Approved :: MIT License
Classifier: Natural Language :: English
Classifier: Programming Language :: Python :: 3 :: Only
Classifier: Programming Language :: Python :: 3.6
Classifier: Programming Language :: Python :: 3.7
Classifier: Programming Language :: Python :: 3.8
Classifier: Operating System :: OS Independent
Classifier: Topic :: Software Development :: Libraries
Requires-Python: >=3.6
Requires-Dist: nozomi
